[{"player_name":"Justin Jefferson","pos":"WR","total_points":"87.10","proj_points":"122.24","avg_points":"12.44","pct_perform":"71.25","injury_stat":"ACTIVE"},{"player_name":"Kyler Murray","pos":"QB","total_points":"93.78","proj_points":"170.00","avg_points":"18.76","pct_perform":"55.16","injury_stat":"QUESTIONABLE"},{"player_name":"Josh Jacobs","pos":"RB","total_points":"127.30","proj_points":"123.36","avg_points":"18.19","pct_perform":"103.19","injury_stat":"ACTIVE"},{"player_name":"Justin Fields","pos":"QB","total_points":"119.86","proj_points":"143.76","avg_points":"17.12","pct_perform":"83.38","injury_stat":"ACTIVE"},{"player_name":"Tetairoa McMillan","pos":"WR","total_points":"81.70","proj_points":"91.20","avg_points":"10.21","pct_perform":"89.58","injury_stat":"ACTIVE"},{"player_name":"Mark Andrews","pos":"TE","total_points":"51.20","proj_points":"74.40","avg_points":"7.31","pct_perform":"68.82","injury_stat":"ACTIVE"},{"player_name":"Keon Coleman","pos":"WR","total_points":"50.20","proj_points":"81.36","avg_points":"7.17","pct_perform":"61.70","injury_stat":"ACTIVE"},{"player_name":"Javonte Williams","pos":"RB","total_points":"136.60","proj_points":"92.64","avg_points":"17.07","pct_perform":"147.45","injury_stat":"ACTIVE"},{"player_name":"Nick Chubb","pos":"RB","total_points":"54.50","proj_points":"53.44","avg_points":"7.79","pct_perform":"101.98","injury_stat":"ACTIVE"},{"player_name":"Darnell Mooney","pos":"WR","total_points":"21.30","proj_points":"66.00","avg_points":"4.26","pct_perform":"32.27","injury_stat":"ACTIVE"},{"player_name":"Kyle Pitts Sr.","pos":"TE","total_points":"69.65","proj_points":"61.44","avg_points":"9.95","pct_perform":"113.36","injury_stat":"ACTIVE"},{"player_name":"Quentin Johnston","pos":"WR","total_points":"83.40","proj_points":"64.48","avg_points":"11.91","pct_perform":"129.34","injury_stat":"ACTIVE"},{"player_name":"Carson Wentz","pos":"QB","total_points":"78.34","proj_points":"1.44","avg_points":"15.67","pct_perform":"5440.28","injury_stat":"INJURY_RESERVE"},{"player_name":"Theo Johnson","pos":"TE","total_points":"62.45","proj_points":"51.44","avg_points":"7.81","pct_perform":"121.40","injury_stat":"ACTIVE"},{"player_name":"Marvin Mims Jr.","pos":"WR","total_points":"49.80","proj_points":"59.84","avg_points":"6.23","pct_perform":"83.22","injury_stat":"QUESTIONABLE"},{"player_name":"Chris Godwin Jr.","pos":"WR","total_points":"8.20","proj_points":"93.36","avg_points":"4.10","pct_perform":"8.78","injury_stat":"OUT"},{"player_name":"Jaylin Lane","pos":"WR","total_points":"26.40","proj_points":"8.64","avg_points":"3.30","pct_perform":"305.56","injury_stat":"ACTIVE"}]