[
  {
    "player_name": "Drake Maye",
    "pos": "QB",
    "slot": "QB",
    "points": 35.28,
    "projected": 22.97
  },
  {
    "player_name": "Michael Pittman Jr.",
    "pos": "WR",
    "slot": "WR",
    "points": 19.5,
    "projected": 10.97
  },
  {
    "player_name": "Khalil Shakir",
    "pos": "WR",
    "slot": "WR",
    "points": 17.8,
    "projected": 9.42
  },
  {
    "player_name": "Woody Marks",
    "pos": "RB",
    "slot": "RB",
    "points": 13.1,
    "projected": 9.71
  },
  {
    "player_name": "Alvin Kamara",
    "pos": "RB",
    "slot": "RB",
    "points": 5.5,
    "projected": 12.13
  },
  {
    "player_name": "Harold Fannin Jr.",
    "pos": "TE",
    "slot": "TE",
    "points": 16.9,
    "projected": 8.51
  },
  {
    "player_name": "George Pickens",
    "pos": "WR",
    "slot": "RB/WR/TE",
    "points": 11.3,
    "projected": 11.99
  },
  {
    "player_name": "Tre' Harris",
    "pos": "WR",
    "slot": "RB/WR/TE",
    "points": 7.8,
    "projected": 2.06
  },
  {
    "player_name": "Justin Herbert",
    "pos": "QB",
    "slot": "OP",
    "points": 33.28,
    "projected": 25.37
  }
]