[{"player_name":"Josh Allen","pos":"QB","slot":"QB","points":51.88,"projected":21.75},{"player_name":"Davante Adams","pos":"WR","slot":"WR","points":21.4,"projected":12.13},{"player_name":"Drake London","pos":"WR","slot":"RB/WR/TE","points":9.5,"projected":12.5},{"player_name":"George Pickens","pos":"WR","slot":"WR","points":0.0,"projected":0.0},{"player_name":"Jakobi Meyers","pos":"WR","slot":"WR","points":10.2,"projected":11.6},{"player_name":"DeAndre Hopkins","pos":"WR","slot":"RB/WR/TE","points":11.2,"projected":8.33},{"player_name":"T.J. Hockenson","pos":"TE","slot":"TE","points":6.5,"projected":8.84},{"player_name":"Bucky Irving","pos":"RB","slot":"RB","points":2.3,"projected":14.31},{"player_name":"Kareem Hunt","pos":"RB","slot":"RB","points":3.4,"projected":8.13},{"player_name":"Will Levis","pos":"QB","slot":"OP","points":7.02,"projected":17.24}]