[{"player_name":"Caleb Williams","pos":"QB","slot":"QB","points":19.48,"projected":17.58},{"player_name":"Rome Odunze","pos":"WR","slot":"WR","points":28.3,"projected":11.2},{"player_name":"DK Metcalf","pos":"WR","slot":"WR","points":9.5,"projected":12.33},{"player_name":"Christian McCaffrey","pos":"RB","slot":"RB","points":19.7,"projected":19.69},{"player_name":"Rachaad White","pos":"RB","slot":"RB","points":13.6,"projected":5.9},{"player_name":"Travis Kelce","pos":"TE","slot":"TE","points":9.1,"projected":11.02},{"player_name":"D'Andre Swift","pos":"RB","slot":"RB/WR/TE","points":12.4,"projected":12.89},{"player_name":"Chris Olave","pos":"WR","slot":"RB/WR/TE","points":8.4,"projected":10.07},{"player_name":"Jalen Hurts","pos":"QB","slot":"OP","points":12.04,"projected":22.83}]