[
  {
    "player_name": "Trevor Lawrence",
    "pos": "QB",
    "slot": "QB",
    "projected": 15.9,
    "opponent": "IND"
  },
  {
    "player_name": "Drake London",
    "pos": "WR",
    "slot": "WR",
    "projected": 12.86,
    "opponent": "SEA"
  },
  {
    "player_name": "Courtland Sutton",
    "pos": "WR",
    "slot": "WR",
    "projected": 9.72,
    "opponent": "LV"
  },
  {
    "player_name": "Saquon Barkley",
    "pos": "RB",
    "slot": "RB",
    "projected": 12.96,
    "opponent": "LAC"
  },
  {
    "player_name": "Aaron Jones Sr.",
    "pos": "RB",
    "slot": "RB",
    "projected": 11.32,
    "opponent": "WSH"
  },
  {
    "player_name": "Zach Ertz",
    "pos": "TE",
    "slot": "TE",
    "projected": 8.42,
    "opponent": "MIN"
  },
  {
    "player_name": "Tony Pollard",
    "pos": "RB",
    "slot": "RB/WR/TE",
    "projected": 9.34,
    "opponent": "CLE"
  },
  {
    "player_name": "Jakobi Meyers",
    "pos": "WR",
    "slot": "RB/WR/TE",
    "projected": 8.7,
    "opponent": "IND"
  },
  {
    "player_name": "Trey Benson",
    "pos": "RB",
    "slot": "OP",
    "projected": 7.19,
    "opponent": "LAR"
  }
]