[
  {
    "player_name": "Tyreek Hill",
    "pos": "WR",
    "slot": "RB/WR/TE",
    "points": 10.2,
    "projected": 15.23
  },
  {
    "player_name": "Joe Burrow",
    "pos": "QB",
    "slot": "QB",
    "points": 12.86,
    "projected": 17.99
  },
  {
    "player_name": "Brock Purdy",
    "pos": "QB",
    "slot": "OP",
    "points": 26.0,
    "projected": 20.23
  },
  {
    "player_name": "Joe Mixon",
    "pos": "RB",
    "slot": "RB",
    "points": 21.4,
    "projected": 17.43
  },
  {
    "player_name": "Malik Nabers",
    "pos": "WR",
    "slot": "WR",
    "points": 10.6,
    "projected": 15.19
  },
  {
    "player_name": "D'Andre Swift",
    "pos": "RB",
    "slot": "RB",
    "points": 18.9,
    "projected": 15.02
  },
  {
    "player_name": "George Kittle",
    "pos": "TE",
    "slot": "RB/WR/TE",
    "points": 21.8,
    "projected": 12.44
  },
  {
    "player_name": "Rashod Bateman",
    "pos": "WR",
    "slot": "WR",
    "points": 3.3,
    "projected": 6.49
  },
  {
    "player_name": "Hunter Henry",
    "pos": "TE",
    "slot": "TE",
    "points": 7.0,
    "projected": 8.28
  },
  {
    "player_name": "Tim Patrick",
    "pos": "WR",
    "slot": "WR",
    "points": 0.0,
    "projected": 6.26
  }
]