[{"player_name":"Ashton Jeanty","pos":"RB","slot":"RB","points":4.8,"projected":13.35},{"player_name":"Jared Goff","pos":"QB","slot":"QB","points":21.66,"projected":24.12},{"player_name":"James Cook III","pos":"RB","slot":"RB","points":10.1,"projected":20.23},{"player_name":"Tyler Warren","pos":"TE","slot":"TE","points":3.2,"projected":11.66},{"player_name":"Romeo Doubs","pos":"WR","slot":"WR","points":0.0,"projected":8.6},{"player_name":"Jacoby Brissett","pos":"QB","slot":"OP","points":16.54,"projected":17.47},{"player_name":"Chris Rodriguez Jr.","pos":"RB","slot":"RB/WR/TE","points":5.2,"projected":8.62},{"player_name":"Jayden Higgins","pos":"WR","slot":"WR","points":4.9,"projected":8.13},{"player_name":"Blake Corum","pos":"RB","slot":"RB/WR/TE","points":25.6,"projected":6.64}]