[{"category":"Record","value":"4-2-0"},{"category":"Points For","value":"749.53"},{"category":"Avg Points For","value":"124.92"},{"category":"Points Against","value":"702.84"},{"category":"Avg Points Against","value":"117.14"},{"category":"Points Left on Bench","value":"50.23"},{"category":"Efficiency","value":"93.72%"},{"category":"Current Streak","value":"1 W"},{"category":"Longest Win Streak","value":"2"},{"category":"Longest Losing Streak","value":"1"},{"category":"Expected Wins","value":"3.818"},{"category":"Actual Wins","value":"4"},{"category":"Luck Factor","value":"0.182"},{"category":"Close Games","value":"0-0"},{"category":"Season Pattern","value":"WLWWLW"}]