[
  {
    "team": "Michael's Managable Team",
    "round": 2,
    "pick": 7,
    "player_name": "Justin Herbert",
    "points": "37.4",
    "before_trade": "37.4",
    "after_trade": "0.0",
    "draft_position": 19,
    "value_diff": "18.4",
    "grade": "A"
  },
  {
    "team": "To Infinity and Bijan!",
    "round": 16,
    "pick": 4,
    "player_name": "Quentin Johnston",
    "points": "22.4",
    "before_trade": "22.4",
    "after_trade": "0.0",
    "draft_position": 184,
    "value_diff": "17.2",
    "grade": "A"
  },
  {
    "team": "To Infinity and Bijan!",
    "round": 10,
    "pick": 4,
    "player_name": "Javonte Williams",
    "points": "19.4",
    "before_trade": "19.4",
    "after_trade": "0.0",
    "draft_position": 112,
    "value_diff": "7.8",
    "grade": "A"
  },
  {
    "team": "Hamlin My Business ",
    "round": 11,
    "pick": 2,
    "player_name": "Keenan Allen",
    "points": "16.3",
    "before_trade": "16.3",
    "after_trade": "0.0",
    "draft_position": 122,
    "value_diff": "7.5",
    "grade": "A"
  },
  {
    "team": "Emma's Excellent Team",
    "round": 11,
    "pick": 3,
    "player_name": "Hollywood Brown",
    "points": "14.9",
    "before_trade": "14.9",
    "after_trade": "0.0",
    "draft_position": 123,
    "value_diff": "6.8",
    "grade": "A"
  }
]