[
  {
    "category": "Record",
    "value": "7-4-0"
  },
  {
    "category": "Points For",
    "value": "1441.98"
  },
  {
    "category": "Avg Points For",
    "value": "131.09"
  },
  {
    "category": "Points Against",
    "value": "1234.21"
  },
  {
    "category": "Avg Points Against",
    "value": "112.20"
  },
  {
    "category": "Points Left on Bench",
    "value": "214.38"
  },
  {
    "category": "Efficiency",
    "value": "87.06%"
  },
  {
    "category": "Current Streak",
    "value": "2 L"
  },
  {
    "category": "Longest Win Streak",
    "value": "4"
  },
  {
    "category": "Longest Losing Streak",
    "value": "2"
  },
  {
    "category": "Expected Wins",
    "value": "7.182"
  },
  {
    "category": "Actual Wins",
    "value": "7"
  },
  {
    "category": "Luck Factor",
    "value": "-0.182"
  },
  {
    "category": "Close Games",
    "value": "1-1"
  },
  {
    "category": "Season Pattern",
    "value": "WWWLLWWWWLL"
  }
]