[
  {
    "week": "Week 1",
    "efficiency": "92.0%"
  },
  {
    "week": "Week 2",
    "efficiency": "71.7%"
  },
  {
    "week": "Week 3",
    "efficiency": "90.0%"
  },
  {
    "week": "Week 4",
    "efficiency": "80.3%"
  },
  {
    "week": "Week 5",
    "efficiency": "89.5%"
  },
  {
    "week": "Week 6",
    "efficiency": "78.3%"
  },
  {
    "week": "Week 7",
    "efficiency": "85.6%"
  },
  {
    "week": "Week 8",
    "efficiency": "81.2%"
  },
  {
    "week": "Week 9",
    "efficiency": "86.1%"
  },
  {
    "week": "Week 10",
    "efficiency": "93.3%"
  },
  {
    "week": "Week 11",
    "efficiency": "90.3%"
  },
  {
    "week": "Week 12",
    "efficiency": "99.9%"
  },
  {
    "week": "Week 13",
    "efficiency": "97.2%"
  },
  {
    "week": "Week 14",
    "efficiency": "90.8%"
  },
  {
    "week": "Week 15",
    "efficiency": "69.6%"
  }
]