{
  "title": {
    "text": "Lineup Efficiency Trends",
    "left": "center",
    "show": false
  },
  "tooltip": {
    "trigger": "axis"
  },
  "legend": {
    "data": [
      "90s",
      "HMB",
      "MMT",
      "ARV",
      "TTC",
      "JST",
      "TOM",
      "TIB",
      "KTT",
      "RRT",
      "EET",
      "BTE"
    ],
    "orient": "vertical",
    "right": 0,
    "top": "middle"
  },
  "xAxis": {
    "type": "category",
    "data": [
      "Week 1",
      "Week 2",
      "Week 3",
      "Week 4"
    ]
  },
  "yAxis": {
    "type": "value",
    "name": "Efficiency %"
  },
  "series": [
    {
      "name": "90s",
      "type": "line",
      "data": [
        88.5,
        88.3,
        93.2,
        94.2
      ]
    },
    {
      "name": "HMB",
      "type": "line",
      "data": [
        92.6,
        85.2,
        86.9,
        83.0
      ]
    },
    {
      "name": "MMT",
      "type": "line",
      "data": [
        75.5,
        86.5,
        92.7,
        78.0
      ]
    },
    {
      "name": "ARV",
      "type": "line",
      "data": [
        84.2,
        85.0,
        96.4,
        100.0
      ]
    },
    {
      "name": "TTC",
      "type": "line",
      "data": [
        90.7,
        85.5,
        91.1,
        88.4
      ]
    },
    {
      "name": "JST",
      "type": "line",
      "data": [
        91.7,
        95.2,
        88.0,
        83.4
      ]
    },
    {
      "name": "TOM",
      "type": "line",
      "data": [
        89.1,
        92.5,
        83.6,
        83.3
      ]
    },
    {
      "name": "TIB",
      "type": "line",
      "data": [
        79.6,
        77.4,
        68.0,
        77.5
      ]
    },
    {
      "name": "KTT",
      "type": "line",
      "data": [
        83.0,
        82.6,
        97.1,
        84.6
      ]
    },
    {
      "name": "RRT",
      "type": "line",
      "data": [
        81.4,
        85.3,
        96.9,
        93.0
      ]
    },
    {
      "name": "EET",
      "type": "line",
      "data": [
        88.3,
        66.4,
        97.1,
        78.0
      ]
    },
    {
      "name": "BTE",
      "type": "line",
      "data": [
        77.9,
        74.8,
        79.9,
        76.6
      ]
    }
  ],
  "grid": {
    "right": "10%",
    "left": "5%"
  }
}