[{"id":3916387,"name":"Lamar Jackson","position":"QB","team":"Who Killed Charbonnet Ramsey?","total_points":357.5,"avg_points":25.54,"ros_projection":35.74},{"id":4362628,"name":"Ja'Marr Chase","position":"WR","team":"Who Killed Charbonnet Ramsey?","total_points":284.8,"avg_points":20.34,"ros_projection":27.88},{"id":4426515,"name":"Puka Nacua","position":"WR","team":"Who Killed Charbonnet Ramsey?","total_points":139.6,"avg_points":15.51,"ros_projection":25.14},{"id":3043078,"name":"Derrick Henry","position":"RB","team":"Who Killed Charbonnet Ramsey?","total_points":254.4,"avg_points":18.17,"ros_projection":25.09},{"id":3915416,"name":"DJ Moore","position":"WR","team":"Who Killed Charbonnet Ramsey?","total_points":151.8,"avg_points":10.84,"ros_projection":21.75},{"id":4431611,"name":"Caleb Williams","position":"QB","team":"Who Killed Charbonnet Ramsey?","total_points":214.28,"avg_points":15.31,"ros_projection":29.67},{"id":3116365,"name":"Mark Andrews","position":"TE","team":"Who Killed Charbonnet Ramsey?","total_points":122.3,"avg_points":8.74,"ros_projection":18.02},{"id":4635008,"name":"Keon Coleman","position":"WR","team":"Who Killed Charbonnet Ramsey?","total_points":79.6,"avg_points":7.96,"ros_projection":16.53},{"id":4428557,"name":"Tyjae Spears","position":"RB","team":"Who Killed Charbonnet Ramsey?","total_points":66.7,"avg_points":6.67,"ros_projection":17.71},{"id":4038815,"name":"Rico Dowdle","position":"RB","team":"Who Killed Charbonnet Ramsey?","total_points":147.0,"avg_points":11.31,"ros_projection":15.84},{"id":4688813,"name":"Josh Downs","position":"WR","team":"Who Killed Charbonnet Ramsey?","total_points":115.8,"avg_points":10.53,"ros_projection":10.37},{"id":4430834,"name":"Jalen McMillan","position":"WR","team":"Who Killed Charbonnet Ramsey?","total_points":65.7,"avg_points":6.57,"ros_projection":11.14},{"id":4361579,"name":"Javonte Williams","position":"RB","team":"Who Killed Charbonnet Ramsey?","total_points":112.8,"avg_points":8.06,"ros_projection":18.91},{"id":2976499,"name":"Amari Cooper","position":"WR","team":"Who Killed Charbonnet Ramsey?","total_points":86.1,"avg_points":7.17,"ros_projection":20.34},{"id":4432665,"name":"Brock Bowers","position":"TE","team":"Who Killed Charbonnet Ramsey?","total_points":167.2,"avg_points":11.94,"ros_projection":13.61},{"id":4241479,"name":"Tua Tagovailoa","position":"QB","team":"Who Killed Charbonnet Ramsey?","total_points":169.08,"avg_points":16.91,"ros_projection":28.29},{"id":4373626,"name":"Tyler Allgeier","position":"RB","team":"Who Killed Charbonnet Ramsey?","total_points":86.3,"avg_points":6.16,"ros_projection":14.97},{"id":3728262,"name":"Ray-Ray McCloud III","position":"WR","team":"Who Killed Charbonnet Ramsey?","total_points":93.5,"avg_points":6.68,"ros_projection":9.47},{"id":4040715,"name":"Jalen Hurts","position":"QB","team":"Pink Pony Club","total_points":310.58,"avg_points":22.18,"ros_projection":36.98},{"id":4429795,"name":"Jahmyr Gibbs","position":"RB","team":"Pink Pony Club","total_points":245.7,"avg_points":17.55,"ros_projection":25.08},{"id":4430737,"name":"Kyren Williams","position":"RB","team":"Pink Pony Club","total_points":221.0,"avg_points":15.79,"ros_projection":25.36},{"id":3126486,"name":"Deebo Samuel Sr.","position":"WR","team":"Pink Pony Club","total_points":97.9,"avg_points":7.53,"ros_projection":22.36},{"id":4426348,"name":"Jayden Daniels","position":"QB","team":"Pink Pony Club","total_points":285.4,"avg_points":20.39,"ros_projection":30.11},{"id":3045147,"name":"James Conner","position":"RB","team":"Pink Pony Club","total_points":203.9,"avg_points":14.56,"ros_projection":18.96},{"id":3121422,"name":"Terry McLaurin","position":"WR","team":"Pink Pony Club","total_points":195.1,"avg_points":13.94,"ros_projection":18.37},{"id":4432773,"name":"Brian Thomas Jr.","position":"WR","team":"Pink Pony Club","total_points":182.6,"avg_points":13.04,"ros_projection":16.58},{"id":4373678,"name":"Khalil Shakir","position":"WR","team":"Pink Pony Club","total_points":137.3,"avg_points":10.56,"ros_projection":14.53},{"id":4360516,"name":"Tyrone Tracy Jr.","position":"RB","team":"Pink Pony Club","total_points":132.5,"avg_points":9.46,"ros_projection":8.46},{"id":4258173,"name":"Nico Collins","position":"WR","team":"Pink Pony Club","total_points":147.4,"avg_points":16.38,"ros_projection":22.43},{"id":4360939,"name":"Rashod Bateman","position":"WR","team":"Pink Pony Club","total_points":126.4,"avg_points":9.03,"ros_projection":10.81},{"id":4243331,"name":"Cade Otton","position":"TE","team":"Pink Pony Club","total_points":111.1,"avg_points":7.94,"ros_projection":10.34},{"id":16460,"name":"Adam Thielen","position":"WR","team":"Pink Pony Club","total_points":70.3,"avg_points":10.04,"ros_projection":15.81},{"id":4372561,"name":"Isaac Guerendo","position":"RB","team":"Pink Pony Club","total_points":74.3,"avg_points":5.31,"ros_projection":4.42},{"id":4430104,"name":"Sincere McCormick","position":"RB","team":"Pink Pony Club","total_points":24.2,"avg_points":4.84,"ros_projection":0.0},{"id":2969939,"name":"Jameis Winston","position":"QB","team":"Pink Pony Club","total_points":131.14,"avg_points":10.93,"ros_projection":3.32},{"id":3929645,"name":"Juwan Johnson","position":"TE","team":"Pink Pony Club","total_points":73.5,"avg_points":5.25,"ros_projection":11.44},{"id":3139477,"name":"Patrick Mahomes","position":"QB","team":"Tom and Jerry","total_points":232.82,"avg_points":16.63,"ros_projection":36.2},{"id":4047646,"name":"A.J. Brown","position":"WR","team":"Tom and Jerry","total_points":152.6,"avg_points":13.87,"ros_projection":25.28},{"id":4036378,"name":"Jordan Love","position":"QB","team":"Tom and Jerry","total_points":205.62,"avg_points":17.14,"ros_projection":24.32},{"id":3054850,"name":"Alvin Kamara","position":"RB","team":"Tom and Jerry","total_points":231.3,"avg_points":16.52,"ros_projection":23.2},{"id":4047365,"name":"Josh Jacobs","position":"RB","team":"Tom and Jerry","total_points":234.4,"avg_points":16.74,"ros_projection":23.04},{"id":4430878,"name":"Jaxon Smith-Njigba","position":"WR","team":"Tom and Jerry","total_points":175.0,"avg_points":12.5,"ros_projection":18.08},{"id":3052587,"name":"Baker Mayfield","position":"QB","team":"Tom and Jerry","total_points":287.28,"avg_points":20.52,"ros_projection":28.87},{"id":4241463,"name":"Jerry Jeudy","position":"WR","team":"Tom and Jerry","total_points":168.2,"avg_points":12.01,"ros_projection":17.17},{"id":4038441,"name":"Justice Hill","position":"RB","team":"Tom and Jerry","total_points":103.1,"avg_points":7.36,"ros_projection":9.1},{"id":4360078,"name":"Alec Pierce","position":"WR","team":"Tom and Jerry","total_points":109.0,"avg_points":7.79,"ros_projection":5.0},{"id":4572680,"name":"Tucker Kraft","position":"TE","team":"Tom and Jerry","total_points":118.4,"avg_points":8.46,"ros_projection":8.35},{"id":4372019,"name":"Jerome Ford","position":"RB","team":"Tom and Jerry","total_points":91.7,"avg_points":7.64,"ros_projection":15.03},{"id":3886598,"name":"Jauan Jennings","position":"WR","team":"Tom and Jerry","total_points":146.0,"avg_points":12.17,"ros_projection":7.02},{"id":4366031,"name":"Tank Dell","position":"WR","team":"Tom and Jerry","total_points":95.7,"avg_points":7.36,"ros_projection":20.78},{"id":4242355,"name":"Jake Ferguson","position":"TE","team":"Tom and Jerry","total_points":64.4,"avg_points":5.85,"ros_projection":15.64},{"id":3045138,"name":"Mike Williams","position":"WR","team":"Tom and Jerry","total_points":39.4,"avg_points":2.63,"ros_projection":15.95},{"id":3054212,"name":"Jonnu Smith","position":"TE","team":"Tom and Jerry","total_points":144.9,"avg_points":10.35,"ros_projection":7.96},{"id":4262921,"name":"Justin Jefferson","position":"WR","team":"Hit and Ruggs","total_points":214.48,"avg_points":15.32,"ros_projection":26.96},{"id":4427366,"name":"Breece Hall","position":"RB","team":"Hit and Ruggs","total_points":178.4,"avg_points":13.72,"ros_projection":30.06},{"id":4429160,"name":"De'Von Achane","position":"RB","team":"Hit and Ruggs","total_points":210.0,"avg_points":15.0,"ros_projection":22.09},{"id":4432708,"name":"Marvin Harrison Jr.","position":"WR","team":"Hit and Ruggs","total_points":132.2,"avg_points":9.44,"ros_projection":21.97},{"id":4372016,"name":"Jaylen Waddle","position":"WR","team":"Hit and Ruggs","total_points":113.6,"avg_points":8.11,"ros_projection":21.04},{"id":2977187,"name":"Cooper Kupp","position":"WR","team":"Hit and Ruggs","total_points":134.2,"avg_points":13.42,"ros_projection":21.05},{"id":4361307,"name":"Trey McBride","position":"TE","team":"Hit and Ruggs","total_points":150.5,"avg_points":11.58,"ros_projection":16.58},{"id":3046779,"name":"Jared Goff","position":"QB","team":"Hit and Ruggs","total_points":263.56,"avg_points":18.83,"ros_projection":27.64},{"id":3932905,"name":"Diontae Johnson","position":"WR","team":"Hit and Ruggs","total_points":70.4,"avg_points":6.4,"ros_projection":20.32},{"id":4431299,"name":"Rome Odunze","position":"WR","team":"Hit and Ruggs","total_points":105.4,"avg_points":7.53,"ros_projection":17.1},{"id":4362238,"name":"Chase Brown","position":"RB","team":"Hit and Ruggs","total_points":204.5,"avg_points":14.61,"ros_projection":17.21},{"id":15864,"name":"Geno Smith","position":"QB","team":"Hit and Ruggs","total_points":210.02,"avg_points":15.0,"ros_projection":26.71},{"id":3128390,"name":"Allen Lazard","position":"WR","team":"Hit and Ruggs","total_points":88.5,"avg_points":9.83,"ros_projection":4.99},{"id":3912547,"name":"Sam Darnold","position":"QB","team":"Hit and Ruggs","total_points":252.6,"avg_points":18.04,"ros_projection":22.65},{"id":4685247,"name":"Braelon Allen","position":"RB","team":"Hit and Ruggs","total_points":68.3,"avg_points":4.88,"ros_projection":8.1},{"id":4569587,"name":"Wan'Dale Robinson","position":"WR","team":"Hit and Ruggs","total_points":101.6,"avg_points":7.26,"ros_projection":12.05},{"id":4429501,"name":"Ray Davis","position":"RB","team":"Hit and Ruggs","total_points":88.9,"avg_points":6.35,"ros_projection":8.08},{"id":4360294,"name":"Antonio Gibson","position":"RB","team":"Hit and Ruggs","total_points":72.9,"avg_points":5.21,"ros_projection":14.37},{"id":4241389,"name":"CeeDee Lamb","position":"WR","team":"Michael's Managable Team","total_points":198.9,"avg_points":14.21,"ros_projection":30.62},{"id":3929630,"name":"Saquon Barkley","position":"RB","team":"Michael's Managable Team","total_points":293.9,"avg_points":20.99,"ros_projection":26.99},{"id":4430027,"name":"Sam LaPorta","position":"TE","team":"Michael's Managable Team","total_points":107.1,"avg_points":8.24,"ros_projection":19.73},{"id":4379399,"name":"James Cook","position":"RB","team":"Michael's Managable Team","total_points":204.5,"avg_points":15.73,"ros_projection":23.21},{"id":4569173,"name":"Rhamondre Stevenson","position":"RB","team":"Michael's Managable Team","total_points":147.5,"avg_points":11.35,"ros_projection":19.87},{"id":4569987,"name":"Jaylen Warren","position":"RB","team":"Michael's Managable Team","total_points":77.6,"avg_points":6.47,"ros_projection":17.72},{"id":4430034,"name":"Xavier Legette","position":"WR","team":"Michael's Managable Team","total_points":90.8,"avg_points":6.49,"ros_projection":12.78},{"id":4429275,"name":"Trey Benson","position":"RB","team":"Michael's Managable Team","total_points":44.0,"avg_points":3.38,"ros_projection":13.04},{"id":4428850,"name":"Dontayvion Wicks","position":"WR","team":"Michael's Managable Team","total_points":68.5,"avg_points":4.89,"ros_projection":12.04},{"id":4599739,"name":"Kendre Miller","position":"RB","team":"Michael's Managable Team","total_points":20.1,"avg_points":5.03,"ros_projection":6.21},{"id":3915411,"name":"Ty Johnson","position":"RB","team":"Michael's Managable Team","total_points":74.9,"avg_points":5.35,"ros_projection":7.48},{"id":4431452,"name":"Drake Maye","position":"QB","team":"Michael's Managable Team","total_points":149.82,"avg_points":14.98,"ros_projection":24.14},{"id":4427095,"name":"DeMario Douglas","position":"WR","team":"Michael's Managable Team","total_points":91.3,"avg_points":6.52,"ros_projection":15.88},{"id":4038941,"name":"Justin Herbert","position":"QB","team":"Michael's Managable Team","total_points":210.76,"avg_points":15.05,"ros_projection":29.65},{"id":4430807,"name":"Bijan Robinson","position":"RB","team":"To Infinity and Bijan!","total_points":234.3,"avg_points":16.74,"ros_projection":30.67},{"id":4374302,"name":"Amon-Ra St. Brown","position":"WR","team":"To Infinity and Bijan!","total_points":215.98,"avg_points":15.43,"ros_projection":26.96},{"id":16737,"name":"Mike Evans","position":"WR","team":"To Infinity and Bijan!","total_points":154.9,"avg_points":14.08,"ros_projection":23.15},{"id":8439,"name":"Aaron Rodgers","position":"QB","team":"To Infinity and Bijan!","total_points":218.3,"avg_points":15.59,"ros_projection":31.2},{"id":4567048,"name":"Kenneth Walker III","position":"RB","team":"To Infinity and Bijan!","total_points":148.3,"avg_points":14.83,"ros_projection":23.19},{"id":4035687,"name":"Michael Pittman Jr.","position":"WR","team":"To Infinity and Bijan!","total_points":96.8,"avg_points":7.45,"ros_projection":21.32},{"id":4239993,"name":"Tee Higgins","position":"WR","team":"To Infinity and Bijan!","total_points":127.9,"avg_points":14.21,"ros_projection":19.91},{"id":4385690,"name":"Dalton Kincaid","position":"TE","team":"To Infinity and Bijan!","total_points":71.9,"avg_points":6.54,"ros_projection":15.83},{"id":2576414,"name":"Raheem Mostert","position":"RB","team":"To Infinity and Bijan!","total_points":52.9,"avg_points":5.29,"ros_projection":18.54},{"id":4040761,"name":"Devin Singletary","position":"RB","team":"To Infinity and Bijan!","total_points":79.2,"avg_points":6.6,"ros_projection":17.72},{"id":4040655,"name":"Darnell Mooney","position":"WR","team":"To Infinity and Bijan!","total_points":145.8,"avg_points":10.41,"ros_projection":17.2},{"id":2577327,"name":"Tyler Lockett","position":"WR","team":"To Infinity and Bijan!","total_points":86.3,"avg_points":6.16,"ros_projection":15.98},{"id":4258595,"name":"Cole Kmet","position":"TE","team":"To Infinity and Bijan!","total_points":87.7,"avg_points":6.26,"ros_projection":10.45},{"id":4431280,"name":"Troy Franklin","position":"WR","team":"To Infinity and Bijan!","total_points":47.0,"avg_points":3.62,"ros_projection":8.3},{"id":4429025,"name":"Quentin Johnston","position":"WR","team":"To Infinity and Bijan!","total_points":111.5,"avg_points":9.29,"ros_projection":10.66},{"id":14881,"name":"Russell Wilson","position":"QB","team":"To Infinity and Bijan!","total_points":128.18,"avg_points":16.02,"ros_projection":20.77},{"id":3116164,"name":"Mike Gesicki","position":"TE","team":"To Infinity and Bijan!","total_points":82.2,"avg_points":5.87,"ros_projection":7.53},{"id":4429013,"name":"Tank Bigsby","position":"RB","team":"To Infinity and Bijan!","total_points":101.9,"avg_points":7.84,"ros_projection":7.99},{"id":3918298,"name":"Josh Allen","position":"QB","team":"Fantasy Guru Kayden","total_points":344.9,"avg_points":24.64,"ros_projection":36.89},{"id":4242335,"name":"Jonathan Taylor","position":"RB","team":"Fantasy Guru Kayden","total_points":144.8,"avg_points":13.16,"ros_projection":27.78},{"id":4432577,"name":"C.J. Stroud","position":"QB","team":"Fantasy Guru Kayden","total_points":192.22,"avg_points":13.73,"ros_projection":32.54},{"id":16800,"name":"Davante Adams","position":"WR","team":"Fantasy Guru Kayden","total_points":157.5,"avg_points":14.32,"ros_projection":22.29},{"id":4426502,"name":"Drake London","position":"WR","team":"Fantasy Guru Kayden","total_points":172.6,"avg_points":12.33,"ros_projection":21.64},{"id":4426354,"name":"George Pickens","position":"WR","team":"Fantasy Guru Kayden","total_points":127.9,"avg_points":10.66,"ros_projection":20.44},{"id":4360248,"name":"Kyle Pitts","position":"TE","team":"Fantasy Guru Kayden","total_points":91.6,"avg_points":6.54,"ros_projection":16.14},{"id":4241474,"name":"Brian Robinson Jr.","position":"RB","team":"Fantasy Guru Kayden","total_points":138.7,"avg_points":12.61,"ros_projection":18.98},{"id":3916433,"name":"Jakobi Meyers","position":"WR","team":"Fantasy Guru Kayden","total_points":132.0,"avg_points":11.0,"ros_projection":16.33},{"id":15795,"name":"DeAndre Hopkins","position":"WR","team":"Fantasy Guru Kayden","total_points":111.6,"avg_points":7.97,"ros_projection":17.06},{"id":4036133,"name":"T.J. Hockenson","position":"TE","team":"Fantasy Guru Kayden","total_points":51.1,"avg_points":7.3,"ros_projection":11.86},{"id":4596448,"name":"Bucky Irving","position":"RB","team":"Fantasy Guru Kayden","total_points":167.8,"avg_points":11.99,"ros_projection":11.62},{"id":3059915,"name":"Kareem Hunt","position":"RB","team":"Fantasy Guru Kayden","total_points":121.0,"avg_points":11.0,"ros_projection":0.0},{"id":4241401,"name":"Trey Sermon","position":"RB","team":"Fantasy Guru Kayden","total_points":40.8,"avg_points":2.91,"ros_projection":6.31},{"id":2976592,"name":"Sterling Shepard","position":"WR","team":"Fantasy Guru Kayden","total_points":58.8,"avg_points":4.9,"ros_projection":0.0},{"id":15835,"name":"Zach Ertz","position":"TE","team":"Fantasy Guru Kayden","total_points":107.6,"avg_points":7.69,"ros_projection":6.85},{"id":4361418,"name":"Will Levis","position":"QB","team":"Fantasy Guru Kayden","total_points":108.14,"avg_points":9.83,"ros_projection":27.0},{"id":4361529,"name":"Isiah Pacheco","position":"RB","team":"Mama Daughter Duo","total_points":46.1,"avg_points":9.22,"ros_projection":24.69},{"id":4697815,"name":"Rachaad White","position":"RB","team":"Mama Daughter Duo","total_points":162.7,"avg_points":12.52,"ros_projection":23.35},{"id":4047650,"name":"DK Metcalf","position":"WR","team":"Mama Daughter Duo","total_points":126.5,"avg_points":10.54,"ros_projection":22.38},{"id":3925357,"name":"Calvin Ridley","position":"WR","team":"Mama Daughter Duo","total_points":131.5,"avg_points":9.39,"ros_projection":21.52},{"id":4362249,"name":"Jayden Reed","position":"WR","team":"Mama Daughter Duo","total_points":154.7,"avg_points":11.05,"ros_projection":17.56},{"id":3123076,"name":"David Njoku","position":"TE","team":"Mama Daughter Duo","total_points":105.9,"avg_points":10.59,"ros_projection":16.32},{"id":15818,"name":"Keenan Allen","position":"WR","team":"Mama Daughter Duo","total_points":117.8,"avg_points":9.82,"ros_projection":18.82},{"id":3128429,"name":"Courtland Sutton","position":"WR","team":"Mama Daughter Duo","total_points":160.0,"avg_points":11.43,"ros_projection":18.11},{"id":4429205,"name":"Jordan Addison","position":"WR","team":"Mama Daughter Duo","total_points":152.6,"avg_points":12.72,"ros_projection":18.05},{"id":4241416,"name":"Chuba Hubbard","position":"RB","team":"Mama Daughter Duo","total_points":189.6,"avg_points":13.54,"ros_projection":14.26},{"id":4361411,"name":"Pat Freiermuth","position":"TE","team":"Mama Daughter Duo","total_points":106.7,"avg_points":7.62,"ros_projection":12.92},{"id":4426338,"name":"Bo Nix","position":"QB","team":"Mama Daughter Duo","total_points":240.28,"avg_points":17.16,"ros_projection":22.68},{"id":4426385,"name":"Zach Charbonnet","position":"RB","team":"Mama Daughter Duo","total_points":145.4,"avg_points":10.39,"ros_projection":14.38},{"id":4429084,"name":"Anthony Richardson","position":"QB","team":"Mama Daughter Duo","total_points":142.62,"avg_points":14.26,"ros_projection":32.46},{"id":16757,"name":"Derek Carr","position":"QB","team":"Mama Daughter Duo","total_points":150.9,"avg_points":15.09,"ros_projection":25.72},{"id":16731,"name":"Brandin Cooks","position":"WR","team":"Mama Daughter Duo","total_points":40.6,"avg_points":5.8,"ros_projection":14.92},{"id":4428718,"name":"Tre Tucker","position":"WR","team":"Mama Daughter Duo","total_points":87.7,"avg_points":6.26,"ros_projection":12.24},{"id":15847,"name":"Travis Kelce","position":"TE","team":"Abbey Road to Victory","total_points":123.0,"avg_points":8.79,"ros_projection":19.73},{"id":4569618,"name":"Garrett Wilson","position":"WR","team":"Abbey Road to Victory","total_points":171.8,"avg_points":12.27,"ros_projection":24.86},{"id":3917315,"name":"Kyler Murray","position":"QB","team":"Abbey Road to Victory","total_points":232.94,"avg_points":16.64,"ros_projection":31.07},{"id":4239996,"name":"Travis Etienne Jr.","position":"RB","team":"Abbey Road to Victory","total_points":90.5,"avg_points":7.54,"ros_projection":23.77},{"id":4429615,"name":"Zay Flowers","position":"WR","team":"Abbey Road to Victory","total_points":153.0,"avg_points":10.93,"ros_projection":20.85},{"id":4035538,"name":"David Montgomery","position":"RB","team":"Abbey Road to Victory","total_points":203.72,"avg_points":14.55,"ros_projection":19.59},{"id":14880,"name":"Kirk Cousins","position":"QB","team":"Abbey Road to Victory","total_points":176.32,"avg_points":12.59,"ros_projection":29.52},{"id":4683062,"name":"Xavier Worthy","position":"WR","team":"Abbey Road to Victory","total_points":121.8,"avg_points":8.7,"ros_projection":17.42},{"id":4248528,"name":"Christian Watson","position":"WR","team":"Abbey Road to Victory","total_points":88.5,"avg_points":6.81,"ros_projection":18.98},{"id":3916148,"name":"Tony Pollard","position":"RB","team":"Abbey Road to Victory","total_points":167.0,"avg_points":11.93,"ros_projection":18.09},{"id":3051926,"name":"Gus Edwards","position":"RB","team":"Abbey Road to Victory","total_points":43.0,"avg_points":4.3,"ros_projection":15.83},{"id":3128720,"name":"Nick Chubb","position":"RB","team":"Abbey Road to Victory","total_points":60.8,"avg_points":7.6,"ros_projection":14.79},{"id":3121427,"name":"Curtis Samuel","position":"WR","team":"Abbey Road to Victory","total_points":39.5,"avg_points":3.04,"ros_projection":15.87},{"id":4597500,"name":"Adonai Mitchell","position":"WR","team":"Abbey Road to Victory","total_points":34.96,"avg_points":2.5,"ros_projection":12.62},{"id":4048244,"name":"Alexander Mattison","position":"RB","team":"Abbey Road to Victory","total_points":96.4,"avg_points":8.76,"ros_projection":10.17},{"id":4692590,"name":"Jalin Hyatt","position":"WR","team":"Abbey Road to Victory","total_points":8.8,"avg_points":0.68,"ros_projection":12.98},{"id":4241478,"name":"DeVonta Smith","position":"WR","team":"Abbey Road to Victory","total_points":130.3,"avg_points":11.85,"ros_projection":21.56},{"id":3116406,"name":"Tyreek Hill","position":"WR","team":"Hamlin My Business ","total_points":149.3,"avg_points":10.66,"ros_projection":28.94},{"id":3915511,"name":"Joe Burrow","position":"QB","team":"Hamlin My Business ","total_points":300.88,"avg_points":21.49,"ros_projection":32.79},{"id":4361741,"name":"Brock Purdy","position":"QB","team":"Hamlin My Business ","total_points":215.46,"avg_points":16.57,"ros_projection":30.51},{"id":3116385,"name":"Joe Mixon","position":"RB","team":"Hamlin My Business ","total_points":206.7,"avg_points":18.79,"ros_projection":23.21},{"id":4595348,"name":"Malik Nabers","position":"WR","team":"Hamlin My Business ","total_points":161.3,"avg_points":13.44,"ros_projection":21.34},{"id":4259545,"name":"D'Andre Swift","position":"RB","team":"Hamlin My Business ","total_points":164.1,"avg_points":11.72,"ros_projection":19.22},{"id":3040151,"name":"George Kittle","position":"TE","team":"Hamlin My Business ","total_points":164.1,"avg_points":13.68,"ros_projection":16.94},{"id":4241457,"name":"Najee Harris","position":"RB","team":"Hamlin My Business ","total_points":159.7,"avg_points":11.41,"ros_projection":18.94},{"id":4612826,"name":"Ladd McConkey","position":"WR","team":"Hamlin My Business ","total_points":148.8,"avg_points":11.45,"ros_projection":17.19},{"id":4426388,"name":"Jameson Williams","position":"WR","team":"Hamlin My Business ","total_points":131.3,"avg_points":10.94,"ros_projection":15.86},{"id":3046439,"name":"Hunter Henry","position":"TE","team":"Hamlin My Business ","total_points":100.5,"avg_points":7.18,"ros_projection":10.43},{"id":3042519,"name":"Aaron Jones","position":"RB","team":"Hamlin My Business ","total_points":185.6,"avg_points":13.26,"ros_projection":19.8},{"id":12483,"name":"Matthew Stafford","position":"QB","team":"Hamlin My Business ","total_points":199.42,"avg_points":14.24,"ros_projection":28.29},{"id":3929785,"name":"Nick Westbrook-Ikhine","position":"WR","team":"Hamlin My Business ","total_points":98.8,"avg_points":7.06,"ros_projection":2.13},{"id":2576336,"name":"Ameer Abdullah","position":"RB","team":"Hamlin My Business ","total_points":72.0,"avg_points":5.14,"ros_projection":3.93},{"id":3051738,"name":"Marquez Valdes-Scantling","position":"WR","team":"Hamlin My Business ","total_points":70.2,"avg_points":5.85,"ros_projection":2.75},{"id":4569559,"name":"Devaughn Vele","position":"WR","team":"Hamlin My Business ","total_points":60.2,"avg_points":6.02,"ros_projection":3.15},{"id":3043116,"name":"Demarcus Robinson","position":"WR","team":"Hamlin My Business ","total_points":99.3,"avg_points":7.09,"ros_projection":14.59}]